{"msList":[{"organisation":null,"discipline":null,"province":null,"provinceCode":null,"goldM":2,"silverM":4,"bronzeM":3,"goldW":3,"silverW":3,"bronzeW":4,"goldX":0,"silverX":0,"bronzeX":0,"goldTOT":5,"silverTOT":7,"bronzeTOT":7,"totalTOT":19,"medal":{"organisation":"USA","rank":1,"rankTotal":1,"sortRank":1,"rankEqual":"N","sortRankTotal":1,"rankTotalEqual":"N","goldM":2,"silverM":4,"bronzeM":3,"totalM":9,"goldW":3,"silverW":3,"bronzeW":4,"totalW":10,"goldX":0,"silverX":0,"bronzeX":0,"totalX":0,"goldTOT":5,"silverTOT":7,"bronzeTOT":7,"totalTOT":19,"organisationName":"美国","organisationImgUrl":"http://img1.cache.netease.com/pcluster/olympicinfo/post/3ae/a4b/6a9/dbbf4113b3ac3dbd7152a58_90x60.jpg","organisationImgUrl19x13":"http://img1.cache.netease.com/pcluster/olympicinfo/post/3ae/a4b/6a9/dbbf4113b3ac3dbd7152a58_19x13.jpg"},"organisationName":null,"dateText":null,"organisationImgUrl":null,"organisationImgUrl19x13":null,"disciplineName":null},{"organisation":null,"discipline":null,"province":null,"provinceCode":null,"goldM":3,"silverM":2,"bronzeM":2,"goldW":2,"silverW":1,"bronzeW":3,"goldX":0,"silverX":0,"bronzeX":0,"goldTOT":5,"silverTOT":3,"bronzeTOT":5,"totalTOT":13,"medal":{"organisation":"CHN","rank":2,"rankTotal":2,"sortRank":2,"rankEqual":"N","sortRankTotal":2,"rankTotalEqual":"N","goldM":3,"silverM":2,"bronzeM":2,"totalM":7,"goldW":2,"silverW":1,"bronzeW":3,"totalW":6,"goldX":0,"silverX":0,"bronzeX":0,"totalX":0,"goldTOT":5,"silverTOT":3,"bronzeTOT":5,"totalTOT":13,"organisationName":"中国","organisationImgUrl":"http://img1.cache.netease.com/pcluster/olympicinfo/post/377/c47/0e2/bfb023cb4a940aed3ef2b8d_90x60.jpg","organisationImgUrl19x13":"http://img1.cache.netease.com/pcluster/olympicinfo/post/377/c47/0e2/bfb023cb4a940aed3ef2b8d_19x13.jpg"},"organisationName":null,"dateText":null,"organisationImgUrl":null,"organisationImgUrl19x13":null,"disciplineName":null},{"organisation":null,"discipline":null,"province":null,"provinceCode":null,"goldM":1,"silverM":0,"bronzeM":2,"goldW":3,"silverW":0,"bronzeW":1,"goldX":0,"silverX":0,"bronzeX":0,"goldTOT":4,"silverTOT":0,"bronzeTOT":3,"totalTOT":7,"medal":{"organisation":"AUS","rank":3,"rankTotal":6,"sortRank":3,"rankEqual":"N","sortRankTotal":6,"rankTotalEqual":"N","goldM":1,"silverM":0,"bronzeM":2,"totalM":3,"goldW":3,"silverW":0,"bronzeW":1,"totalW":4,"goldX":0,"silverX":0,"bronzeX":0,"totalX":0,"goldTOT":4,"silverTOT":0,"bronzeTOT":3,"totalTOT":7,"organisationName":"澳大利亚","organisationImgUrl":"http://img1.cache.netease.com/pcluster/olympicinfo/post/ddd/956/cc8/52b9bdf418368cd706b92f3_90x60.jpg","organisationImgUrl19x13":"http://img1.cache.netease.com/pcluster/olympicinfo/post/ddd/956/cc8/52b9bdf418368cd706b92f3_19x13.jpg"},"organisationName":null,"dateText":null,"organisationImgUrl":null,"organisationImgUrl19x13":null,"disciplineName":null},{"organisation":null,"discipline":null,"province":null,"provinceCode":null,"goldM":3,"silverM":1,"bronzeM":1,"goldW":0,"silverW":3,"bronzeW":1,"goldX":0,"silverX":0,"bronzeX":0,"goldTOT":3,"silverTOT":4,"bronzeTOT":2,"totalTOT":9,"medal":{"organisation":"ITA","rank":4,"rankTotal":5,"sortRank":4,"rankEqual":"N","sortRankTotal":5,"rankTotalEqual":"N","goldM":3,"silverM":1,"bronzeM":1,"totalM":5,"goldW":0,"silverW":3,"bronzeW":1,"totalW":4,"goldX":0,"silverX":0,"bronzeX":0,"totalX":0,"goldTOT":3,"silverTOT":4,"bronzeTOT":2,"totalTOT":9,"organisationName":"意大利","organisationImgUrl":"http://img1.cache.netease.com/pcluster/olympicinfo/post/fc0/a20/783/711def152e27ce41f2ef678_90x60.jpg","organisationImgUrl19x13":"http://img1.cache.netease.com/pcluster/olympicinfo/post/fc0/a20/783/711def152e27ce41f2ef678_19x13.jpg"},"organisationName":null,"dateText":null,"organisationImgUrl":null,"organisationImgUrl19x13":null,"disciplineName":null},{"organisation":null,"discipline":null,"province":null,"provinceCode":null,"goldM":3,"silverM":0,"bronzeM":3,"goldW":0,"silverW":0,"bronzeW":4,"goldX":0,"silverX":0,"bronzeX":0,"goldTOT":3,"silverTOT":0,"bronzeTOT":7,"totalTOT":10,"medal":{"organisation":"JPN","rank":5,"rankTotal":3,"sortRank":5,"rankEqual":"N","sortRankTotal":3,"rankTotalEqual":"Y","goldM":3,"silverM":0,"bronzeM":3,"totalM":6,"goldW":0,"silverW":0,"bronzeW":4,"totalW":4,"goldX":0,"silverX":0,"bronzeX":0,"totalX":0,"goldTOT":3,"silverTOT":0,"bronzeTOT":7,"totalTOT":10,"organisationName":"日本","organisationImgUrl":"http://img1.cache.netease.com/pcluster/olympicinfo/post/fdf/465/681/debdd16cd0bf91592bccabb_90x60.jpg","organisationImgUrl19x13":"http://img1.cache.netease.com/pcluster/olympicinfo/post/fdf/465/681/debdd16cd0bf91592bccabb_19x13.jpg"},"organisationName":null,"dateText":null,"organisationImgUrl":null,"organisationImgUrl19x13":null,"disciplineName":null},{"organisation":null,"discipline":null,"province":null,"provinceCode":null,"goldM":0,"silverM":0,"bronzeM":0,"goldW":3,"silverW":0,"bronzeW":0,"goldX":0,"silverX":0,"bronzeX":0,"goldTOT":3,"silverTOT":0,"bronzeTOT":0,"totalTOT":3,"medal":{"organisation":"HUN","rank":6,"rankTotal":11,"sortRank":6,"rankEqual":"N","sortRankTotal":11,"rankTotalEqual":"Y","goldM":0,"silverM":0,"bronzeM":0,"totalM":0,"goldW":3,"silverW":0,"bronzeW":0,"totalW":3,"goldX":0,"silverX":0,"bronzeX":0,"totalX":0,"goldTOT":3,"silverTOT":0,"bronzeTOT":0,"totalTOT":3,"organisationName":"匈牙利","organisationImgUrl":"http://img1.cache.netease.com/pcluster/olympicinfo/post/a11/3b3/ccd/ad142d13883b355259d2e89_90x60.jpg","organisationImgUrl19x13":"http://img1.cache.netease.com/pcluster/olympicinfo/post/a11/3b3/ccd/ad142d13883b355259d2e89_19x13.jpg"},"organisationName":null,"dateText":null,"organisationImgUrl":null,"organisationImgUrl19x13":null,"disciplineName":null},{"organisation":null,"discipline":null,"province":null,"provinceCode":null,"goldM":1,"silverM":1,"bronzeM":2,"goldW":1,"silverW":4,"bronzeW":1,"goldX":0,"silverX":0,"bronzeX":0,"goldTOT":2,"silverTOT":5,"bronzeTOT":3,"totalTOT":10,"medal":{"organisation":"RUS","rank":7,"rankTotal":3,"sortRank":7,"rankEqual":"N","sortRankTotal":4,"rankTotalEqual":"Y","goldM":1,"silverM":1,"bronzeM":2,"totalM":4,"goldW":1,"silverW":4,"bronzeW":1,"totalW":6,"goldX":0,"silverX":0,"bronzeX":0,"totalX":0,"goldTOT":2,"silverTOT":5,"bronzeTOT":3,"totalTOT":10,"organisationName":"俄罗斯联邦","organisationImgUrl":"http://img1.cache.netease.com/pcluster/olympicinfo/post/94a/57d/f41/f821faa94c64bf317e9fa12_90x60.jpg","organisationImgUrl19x13":"http://img1.cache.netease.com/pcluster/olympicinfo/post/94a/57d/f41/f821faa94c64bf317e9fa12_19x13.jpg"},"organisationName":null,"dateText":null,"organisationImgUrl":null,"organisationImgUrl19x13":null,"disciplineName":null},{"organisation":null,"discipline":null,"province":null,"provinceCode":null,"goldM":1,"silverM":1,"bronzeM":0,"goldW":1,"silverW":1,"bronzeW":1,"goldX":0,"silverX":0,"bronzeX":0,"goldTOT":2,"silverTOT":2,"bronzeTOT":1,"totalTOT":5,"medal":{"organisation":"KOR","rank":8,"rankTotal":7,"sortRank":8,"rankEqual":"N","sortRankTotal":7,"rankTotalEqual":"N","goldM":1,"silverM":1,"bronzeM":0,"totalM":2,"goldW":1,"silverW":1,"bronzeW":1,"totalW":3,"goldX":0,"silverX":0,"bronzeX":0,"totalX":0,"goldTOT":2,"silverTOT":2,"bronzeTOT":1,"totalTOT":5,"organisationName":"韩国","organisationImgUrl":"http://img1.cache.netease.com/pcluster/olympicinfo/post/7df/616/7ee/23a7b6f489cadb9d943d556_90x60.jpg","organisationImgUrl19x13":"http://img1.cache.netease.com/pcluster/olympicinfo/post/7df/616/7ee/23a7b6f489cadb9d943d556_19x13.jpg"},"organisationName":null,"dateText":null,"organisationImgUrl":null,"organisationImgUrl19x13":null,"disciplineName":null},{"organisation":null,"discipline":null,"province":null,"provinceCode":null,"goldM":0,"silverM":0,"bronzeM":1,"goldW":2,"silverW":1,"bronzeW":0,"goldX":0,"silverX":0,"bronzeX":0,"goldTOT":2,"silverTOT":1,"bronzeTOT":1,"totalTOT":4,"medal":{"organisation":"THA","rank":9,"rankTotal":8,"sortRank":9,"rankEqual":"N","sortRankTotal":8,"rankTotalEqual":"Y","goldM":0,"silverM":0,"bronzeM":1,"totalM":1,"goldW":2,"silverW":1,"bronzeW":0,"totalW":3,"goldX":0,"silverX":0,"bronzeX":0,"totalX":0,"goldTOT":2,"silverTOT":1,"bronzeTOT":1,"totalTOT":4,"organisationName":"泰国","organisationImgUrl":"http://img1.cache.netease.com/pcluster/olympicinfo/post/add/4ad/255/f64b4a04e75b167b30d228b_90x60.jpg","organisationImgUrl19x13":"http://img1.cache.netease.com/pcluster/olympicinfo/post/add/4ad/255/f64b4a04e75b167b30d228b_19x13.jpg"},"organisationName":null,"dateText":null,"organisationImgUrl":null,"organisationImgUrl19x13":null,"disciplineName":null},{"organisation":null,"discipline":null,"province":null,"provinceCode":null,"goldM":1,"silverM":0,"bronzeM":2,"goldW":0,"silverW":1,"bronzeW":0,"goldX":0,"silverX":0,"bronzeX":0,"goldTOT":1,"silverTOT":1,"bronzeTOT":2,"totalTOT":4,"medal":{"organisation":"GBR","rank":10,"rankTotal":8,"sortRank":10,"rankEqual":"N","sortRankTotal":9,"rankTotalEqual":"Y","goldM":1,"silverM":0,"bronzeM":2,"totalM":3,"goldW":0,"silverW":1,"bronzeW":0,"totalW":1,"goldX":0,"silverX":0,"bronzeX":0,"totalX":0,"goldTOT":1,"silverTOT":1,"bronzeTOT":2,"totalTOT":4,"organisationName":"英国","organisationImgUrl":"http://img1.cache.netease.com/pcluster/olympicinfo/post/3cb/999/d32/2ce7d9b328fe828306bb55f_90x60.jpg","organisationImgUrl19x13":"http://img1.cache.netease.com/pcluster/olympicinfo/post/3cb/999/d32/2ce7d9b328fe828306bb55f_19x13.jpg"},"organisationName":null,"dateText":null,"organisationImgUrl":null,"organisationImgUrl19x13":null,"disciplineName":null},{"organisation":null,"discipline":null,"province":null,"provinceCode":null,"goldM":0,"silverM":1,"bronzeM":0,"goldW":1,"silverW":0,"bronzeW":0,"goldX":0,"silverX":0,"bronzeX":0,"goldTOT":1,"silverTOT":1,"bronzeTOT":0,"totalTOT":2,"medal":{"organisation":"BRA","rank":11,"rankTotal":14,"sortRank":11,"rankEqual":"Y","sortRankTotal":14,"rankTotalEqual":"Y","goldM":0,"silverM":1,"bronzeM":0,"totalM":1,"goldW":1,"silverW":0,"bronzeW":0,"totalW":1,"goldX":0,"silverX":0,"bronzeX":0,"totalX":0,"goldTOT":1,"silverTOT":1,"bronzeTOT":0,"totalTOT":2,"organisationName":"巴西","organisationImgUrl":"http://img1.cache.netease.com/pcluster/olympicinfo/post/948/b0a/910/fc589d663680fad93bfbdab_90x60.jpg","organisationImgUrl19x13":"http://img1.cache.netease.com/pcluster/olympicinfo/post/948/b0a/910/fc589d663680fad93bfbdab_19x13.jpg"},"organisationName":null,"dateText":null,"organisationImgUrl":null,"organisationImgUrl19x13":null,"disciplineName":null},{"organisation":null,"discipline":null,"province":null,"provinceCode":null,"goldM":0,"silverM":0,"bronzeM":0,"goldW":1,"silverW":1,"bronzeW":0,"goldX":0,"silverX":0,"bronzeX":0,"goldTOT":1,"silverTOT":1,"bronzeTOT":0,"totalTOT":2,"medal":{"organisation":"SWE","rank":11,"rankTotal":14,"sortRank":12,"rankEqual":"Y","sortRankTotal":15,"rankTotalEqual":"Y","goldM":0,"silverM":0,"bronzeM":0,"totalM":0,"goldW":1,"silverW":1,"bronzeW":0,"totalW":2,"goldX":0,"silverX":0,"bronzeX":0,"totalX":0,"goldTOT":1,"silverTOT":1,"bronzeTOT":0,"totalTOT":2,"organisationName":"瑞典","organisationImgUrl":"http://img1.cache.netease.com/pcluster/olympicinfo/post/205/aba/e12/a1da22052884bdb4ecb3707_90x60.jpg","organisationImgUrl19x13":"http://img1.cache.netease.com/pcluster/olympicinfo/post/205/aba/e12/a1da22052884bdb4ecb3707_19x13.jpg"},"organisationName":null,"dateText":null,"organisationImgUrl":null,"organisationImgUrl19x13":null,"disciplineName":null},{"organisation":null,"discipline":null,"province":null,"provinceCode":null,"goldM":0,"silverM":0,"bronzeM":0,"goldW":1,"silverW":0,"bronzeW":2,"goldX":0,"silverX":0,"bronzeX":0,"goldTOT":1,"silverTOT":0,"bronzeTOT":2,"totalTOT":3,"medal":{"organisation":"TPE","rank":13,"rankTotal":11,"sortRank":13,"rankEqual":"N","sortRankTotal":12,"rankTotalEqual":"Y","goldM":0,"silverM":0,"bronzeM":0,"totalM":0,"goldW":1,"silverW":0,"bronzeW":2,"totalW":3,"goldX":0,"silverX":0,"bronzeX":0,"totalX":0,"goldTOT":1,"silverTOT":0,"bronzeTOT":2,"totalTOT":3,"organisationName":"中华台北","organisationImgUrl":"http://img1.cache.netease.com/pcluster/olympicinfo/post/775/26c/b3b/57b572d72f465387afaad83_90x60.jpeg","organisationImgUrl19x13":"http://img1.cache.netease.com/pcluster/olympicinfo/post/775/26c/b3b/57b572d72f465387afaad83_19x13.jpeg"},"organisationName":null,"dateText":null,"organisationImgUrl":null,"organisationImgUrl19x13":null,"disciplineName":null},{"organisation":null,"discipline":null,"province":null,"provinceCode":null,"goldM":1,"silverM":0,"bronzeM":1,"goldW":0,"silverW":0,"bronzeW":0,"goldX":0,"silverX":0,"bronzeX":0,"goldTOT":1,"silverTOT":0,"bronzeTOT":1,"totalTOT":2,"medal":{"organisation":"BEL","rank":14,"rankTotal":14,"sortRank":14,"rankEqual":"N","sortRankTotal":16,"rankTotalEqual":"Y","goldM":1,"silverM":0,"bronzeM":1,"totalM":2,"goldW":0,"silverW":0,"bronzeW":0,"totalW":0,"goldX":0,"silverX":0,"bronzeX":0,"totalX":0,"goldTOT":1,"silverTOT":0,"bronzeTOT":1,"totalTOT":2,"organisationName":"比利时","organisationImgUrl":"http://img1.cache.netease.com/pcluster/olympicinfo/post/4ba/564/65b/d53ef8f3491bc4606a0829a_90x60.jpg","organisationImgUrl19x13":"http://img1.cache.netease.com/pcluster/olympicinfo/post/4ba/564/65b/d53ef8f3491bc4606a0829a_19x13.jpg"},"organisationName":null,"dateText":null,"organisationImgUrl":null,"organisationImgUrl19x13":null,"disciplineName":null},{"organisation":null,"discipline":null,"province":null,"provinceCode":null,"goldM":0,"silverM":0,"bronzeM":0,"goldW":1,"silverW":0,"bronzeW":0,"goldX":0,"silverX":0,"bronzeX":0,"goldTOT":1,"silverTOT":0,"bronzeTOT":0,"totalTOT":1,"medal":{"organisation":"ARG","rank":15,"rankTotal":22,"sortRank":15,"rankEqual":"Y","sortRankTotal":22,"rankTotalEqual":"Y","goldM":0,"silverM":0,"bronzeM":0,"totalM":0,"goldW":1,"silverW":0,"bronzeW":0,"totalW":1,"goldX":0,"silverX":0,"bronzeX":0,"totalX":0,"goldTOT":1,"silverTOT":0,"bronzeTOT":0,"totalTOT":1,"organisationName":"阿根廷","organisationImgUrl":"http://img1.cache.netease.com/pcluster/olympicinfo/post/7e7/36f/79c/4d51e0e98b27e124731cec9_90x60.jpg","organisationImgUrl19x13":"http://img1.cache.netease.com/pcluster/olympicinfo/post/7e7/36f/79c/4d51e0e98b27e124731cec9_19x13.jpg"},"organisationName":null,"dateText":null,"organisationImgUrl":null,"organisationImgUrl19x13":null,"disciplineName":null},{"organisation":null,"discipline":null,"province":null,"provinceCode":null,"goldM":1,"silverM":0,"bronzeM":0,"goldW":0,"silverW":0,"bronzeW":0,"goldX":0,"silverX":0,"bronzeX":0,"goldTOT":1,"silverTOT":0,"bronzeTOT":0,"totalTOT":1,"medal":{"organisation":"COL","rank":15,"rankTotal":22,"sortRank":16,"rankEqual":"Y","sortRankTotal":23,"rankTotalEqual":"Y","goldM":1,"silverM":0,"bronzeM":0,"totalM":1,"goldW":0,"silverW":0,"bronzeW":0,"totalW":0,"goldX":0,"silverX":0,"bronzeX":0,"totalX":0,"goldTOT":1,"silverTOT":0,"bronzeTOT":0,"totalTOT":1,"organisationName":"哥伦比亚","organisationImgUrl":"http://img1.cache.netease.com/pcluster/olympicinfo/post/04c/130/e19/61690c7f5a071b792c00909_90x60.jpg","organisationImgUrl19x13":"http://img1.cache.netease.com/pcluster/olympicinfo/post/04c/130/e19/61690c7f5a071b792c00909_19x13.jpg"},"organisationName":null,"dateText":null,"organisationImgUrl":null,"organisationImgUrl19x13":null,"disciplineName":null},{"organisation":null,"discipline":null,"province":null,"provinceCode":null,"goldM":1,"silverM":0,"bronzeM":0,"goldW":0,"silverW":0,"bronzeW":0,"goldX":0,"silverX":0,"bronzeX":0,"goldTOT":1,"silverTOT":0,"bronzeTOT":0,"totalTOT":1,"medal":{"organisation":"CRO","rank":15,"rankTotal":22,"sortRank":17,"rankEqual":"Y","sortRankTotal":24,"rankTotalEqual":"Y","goldM":1,"silverM":0,"bronzeM":0,"totalM":1,"goldW":0,"silverW":0,"bronzeW":0,"totalW":0,"goldX":0,"silverX":0,"bronzeX":0,"totalX":0,"goldTOT":1,"silverTOT":0,"bronzeTOT":0,"totalTOT":1,"organisationName":"克罗地亚","organisationImgUrl":"http://img1.cache.netease.com/pcluster/olympicinfo/post/c91/91e/4e5/0e09700a16c9f928393dce8_90x60.jpg","organisationImgUrl19x13":"http://img1.cache.netease.com/pcluster/olympicinfo/post/c91/91e/4e5/0e09700a16c9f928393dce8_19x13.jpg"},"organisationName":null,"dateText":null,"organisationImgUrl":null,"organisationImgUrl19x13":null,"disciplineName":null},{"organisation":null,"discipline":null,"province":null,"provinceCode":null,"goldM":0,"silverM":0,"bronzeM":0,"goldW":1,"silverW":0,"bronzeW":0,"goldX":0,"silverX":0,"bronzeX":0,"goldTOT":1,"silverTOT":0,"bronzeTOT":0,"totalTOT":1,"medal":{"organisation":"KOS","rank":15,"rankTotal":22,"sortRank":18,"rankEqual":"Y","sortRankTotal":25,"rankTotalEqual":"Y","goldM":0,"silverM":0,"bronzeM":0,"totalM":0,"goldW":1,"silverW":0,"bronzeW":0,"totalW":1,"goldX":0,"silverX":0,"bronzeX":0,"totalX":0,"goldTOT":1,"silverTOT":0,"bronzeTOT":0,"totalTOT":1,"organisationName":"科索沃","organisationImgUrl":"http://img1.cache.netease.com/pcluster/olympicinfo/post/8ec/1e0/e15/16845a5ccd1c1ecd3ced347_90x60.png","organisationImgUrl19x13":"http://img1.cache.netease.com/pcluster/olympicinfo/post/8ec/1e0/e15/16845a5ccd1c1ecd3ced347_19x13.png"},"organisationName":null,"dateText":null,"organisationImgUrl":null,"organisationImgUrl19x13":null,"disciplineName":null},{"organisation":null,"discipline":null,"province":null,"provinceCode":null,"goldM":0,"silverM":0,"bronzeM":0,"goldW":1,"silverW":0,"bronzeW":0,"goldX":0,"silverX":0,"bronzeX":0,"goldTOT":1,"silverTOT":0,"bronzeTOT":0,"totalTOT":1,"medal":{"organisation":"NED","rank":15,"rankTotal":22,"sortRank":19,"rankEqual":"Y","sortRankTotal":26,"rankTotalEqual":"Y","goldM":0,"silverM":0,"bronzeM":0,"totalM":0,"goldW":1,"silverW":0,"bronzeW":0,"totalW":1,"goldX":0,"silverX":0,"bronzeX":0,"totalX":0,"goldTOT":1,"silverTOT":0,"bronzeTOT":0,"totalTOT":1,"organisationName":"荷兰","organisationImgUrl":"http://img1.cache.netease.com/pcluster/olympicinfo/post/71f/6e1/38d/a43b55e03f487edb7298d3f_90x60.jpg","organisationImgUrl19x13":"http://img1.cache.netease.com/pcluster/olympicinfo/post/71f/6e1/38d/a43b55e03f487edb7298d3f_19x13.jpg"},"organisationName":null,"dateText":null,"organisationImgUrl":null,"organisationImgUrl19x13":null,"disciplineName":null},{"organisation":null,"discipline":null,"province":null,"provinceCode":null,"goldM":1,"silverM":0,"bronzeM":0,"goldW":0,"silverW":0,"bronzeW":0,"goldX":0,"silverX":0,"bronzeX":0,"goldTOT":1,"silverTOT":0,"bronzeTOT":0,"totalTOT":1,"medal":{"organisation":"VIE","rank":15,"rankTotal":22,"sortRank":20,"rankEqual":"Y","sortRankTotal":27,"rankTotalEqual":"Y","goldM":1,"silverM":0,"bronzeM":0,"totalM":1,"goldW":0,"silverW":0,"bronzeW":0,"totalW":0,"goldX":0,"silverX":0,"bronzeX":0,"totalX":0,"goldTOT":1,"silverTOT":0,"bronzeTOT":0,"totalTOT":1,"organisationName":"越南","organisationImgUrl":"http://img1.cache.netease.com/pcluster/olympicinfo/post/479/9be/333/37f4b01be36cb8e2ea55f3b_90x60.jpg","organisationImgUrl19x13":"http://img1.cache.netease.com/pcluster/olympicinfo/post/479/9be/333/37f4b01be36cb8e2ea55f3b_19x13.jpg"},"organisationName":null,"dateText":null,"organisationImgUrl":null,"organisationImgUrl19x13":null,"disciplineName":null},{"organisation":null,"discipline":null,"province":null,"provinceCode":null,"goldM":0,"silverM":1,"bronzeM":0,"goldW":0,"silverW":1,"bronzeW":0,"goldX":0,"silverX":0,"bronzeX":0,"goldTOT":0,"silverTOT":2,"bronzeTOT":0,"totalTOT":2,"medal":{"organisation":"INA","rank":21,"rankTotal":14,"sortRank":21,"rankEqual":"Y","sortRankTotal":17,"rankTotalEqual":"Y","goldM":0,"silverM":1,"bronzeM":0,"totalM":1,"goldW":0,"silverW":1,"bronzeW":0,"totalW":1,"goldX":0,"silverX":0,"bronzeX":0,"totalX":0,"goldTOT":0,"silverTOT":2,"bronzeTOT":0,"totalTOT":2,"organisationName":"印度尼西亚","organisationImgUrl":"http://img1.cache.netease.com/pcluster/olympicinfo/post/dca/e30/088/1c41a681eed9cef71c9f2bd_90x60.jpg","organisationImgUrl19x13":"http://img1.cache.netease.com/pcluster/olympicinfo/post/dca/e30/088/1c41a681eed9cef71c9f2bd_19x13.jpg"},"organisationName":null,"dateText":null,"organisationImgUrl":null,"organisationImgUrl19x13":null,"disciplineName":null},{"organisation":null,"discipline":null,"province":null,"provinceCode":null,"goldM":0,"silverM":0,"bronzeM":0,"goldW":0,"silverW":2,"bronzeW":0,"goldX":0,"silverX":0,"bronzeX":0,"goldTOT":0,"silverTOT":2,"bronzeTOT":0,"totalTOT":2,"medal":{"organisation":"NZL","rank":21,"rankTotal":14,"sortRank":22,"rankEqual":"Y","sortRankTotal":18,"rankTotalEqual":"Y","goldM":0,"silverM":0,"bronzeM":0,"totalM":0,"goldW":0,"silverW":2,"bronzeW":0,"totalW":2,"goldX":0,"silverX":0,"bronzeX":0,"totalX":0,"goldTOT":0,"silverTOT":2,"bronzeTOT":0,"totalTOT":2,"organisationName":"新西兰","organisationImgUrl":"http://img1.cache.netease.com/pcluster/olympicinfo/post/b86/89c/a15/4fbb1bf819b949692f05e51_90x60.jpg","organisationImgUrl19x13":"http://img1.cache.netease.com/pcluster/olympicinfo/post/b86/89c/a15/4fbb1bf819b949692f05e51_19x13.jpg"},"organisationName":null,"dateText":null,"organisationImgUrl":null,"organisationImgUrl19x13":null,"disciplineName":null},{"organisation":null,"discipline":null,"province":null,"provinceCode":null,"goldM":0,"silverM":2,"bronzeM":0,"goldW":0,"silverW":0,"bronzeW":0,"goldX":0,"silverX":0,"bronzeX":0,"goldTOT":0,"silverTOT":2,"bronzeTOT":0,"totalTOT":2,"medal":{"organisation":"RSA","rank":21,"rankTotal":14,"sortRank":23,"rankEqual":"Y","sortRankTotal":19,"rankTotalEqual":"Y","goldM":0,"silverM":2,"bronzeM":0,"totalM":2,"goldW":0,"silverW":0,"bronzeW":0,"totalW":0,"goldX":0,"silverX":0,"bronzeX":0,"totalX":0,"goldTOT":0,"silverTOT":2,"bronzeTOT":0,"totalTOT":2,"organisationName":"南非","organisationImgUrl":"http://img1.cache.netease.com/pcluster/olympicinfo/post/123/37b/300/f87a6dcf6fd4765216afb1b_90x60.jpg","organisationImgUrl19x13":"http://img1.cache.netease.com/pcluster/olympicinfo/post/123/37b/300/f87a6dcf6fd4765216afb1b_19x13.jpg"},"organisationName":null,"dateText":null,"organisationImgUrl":null,"organisationImgUrl19x13":null,"disciplineName":null},{"organisation":null,"discipline":null,"province":null,"provinceCode":null,"goldM":0,"silverM":0,"bronzeM":0,"goldW":0,"silverW":1,"bronzeW":3,"goldX":0,"silverX":0,"bronzeX":0,"goldTOT":0,"silverTOT":1,"bronzeTOT":3,"totalTOT":4,"medal":{"organisation":"CAN","rank":24,"rankTotal":8,"sortRank":24,"rankEqual":"N","sortRankTotal":10,"rankTotalEqual":"Y","goldM":0,"silverM":0,"bronzeM":0,"totalM":0,"goldW":0,"silverW":1,"bronzeW":3,"totalW":4,"goldX":0,"silverX":0,"bronzeX":0,"totalX":0,"goldTOT":0,"silverTOT":1,"bronzeTOT":3,"totalTOT":4,"organisationName":"加拿大","organisationImgUrl":"http://img1.cache.netease.com/pcluster/olympicinfo/post/c9f/d10/fb7/d6b1d3759c9617a3ec3fde0_90x60.jpg","organisationImgUrl19x13":"http://img1.cache.netease.com/pcluster/olympicinfo/post/c9f/d10/fb7/d6b1d3759c9617a3ec3fde0_19x13.jpg"},"organisationName":null,"dateText":null,"organisationImgUrl":null,"organisationImgUrl19x13":null,"disciplineName":null},{"organisation":null,"discipline":null,"province":null,"provinceCode":null,"goldM":0,"silverM":1,"bronzeM":1,"goldW":0,"silverW":0,"bronzeW":1,"goldX":0,"silverX":0,"bronzeX":0,"goldTOT":0,"silverTOT":1,"bronzeTOT":2,"totalTOT":3,"medal":{"organisation":"KAZ","rank":25,"rankTotal":11,"sortRank":25,"rankEqual":"N","sortRankTotal":13,"rankTotalEqual":"Y","goldM":0,"silverM":1,"bronzeM":1,"totalM":2,"goldW":0,"silverW":0,"bronzeW":1,"totalW":1,"goldX":0,"silverX":0,"bronzeX":0,"totalX":0,"goldTOT":0,"silverTOT":1,"bronzeTOT":2,"totalTOT":3,"organisationName":"哈萨克斯坦","organisationImgUrl":"http://img1.cache.netease.com/pcluster/olympicinfo/post/1d6/82a/8ae/e71ca55e76d1265ec6d5d07_90x60.jpg","organisationImgUrl19x13":"http://img1.cache.netease.com/pcluster/olympicinfo/post/1d6/82a/8ae/e71ca55e76d1265ec6d5d07_19x13.jpg"},"organisationName":null,"dateText":null,"organisationImgUrl":null,"organisationImgUrl19x13":null,"disciplineName":null},{"organisation":null,"discipline":null,"province":null,"provinceCode":null,"goldM":0,"silverM":1,"bronzeM":0,"goldW":0,"silverW":0,"bronzeW":1,"goldX":0,"silverX":0,"bronzeX":0,"goldTOT":0,"silverTOT":1,"bronzeTOT":1,"totalTOT":2,"medal":{"organisation":"UKR","rank":26,"rankTotal":14,"sortRank":26,"rankEqual":"N","sortRankTotal":20,"rankTotalEqual":"Y","goldM":0,"silverM":1,"bronzeM":0,"totalM":1,"goldW":0,"silverW":0,"bronzeW":1,"totalW":1,"goldX":0,"silverX":0,"bronzeX":0,"totalX":0,"goldTOT":0,"silverTOT":1,"bronzeTOT":1,"totalTOT":2,"organisationName":"乌克兰","organisationImgUrl":"http://img1.cache.netease.com/pcluster/olympicinfo/post/e16/981/cd8/070ba92b1671e05bd711953_90x60.jpg","organisationImgUrl19x13":"http://img1.cache.netease.com/pcluster/olympicinfo/post/e16/981/cd8/070ba92b1671e05bd711953_19x13.jpg"},"organisationName":null,"dateText":null,"organisationImgUrl":null,"organisationImgUrl19x13":null,"disciplineName":null},{"organisation":null,"discipline":null,"province":null,"provinceCode":null,"goldM":0,"silverM":1,"bronzeM":0,"goldW":0,"silverW":0,"bronzeW":0,"goldX":0,"silverX":0,"bronzeX":0,"goldTOT":0,"silverTOT":1,"bronzeTOT":0,"totalTOT":1,"medal":{"organisation":"AZE","rank":27,"rankTotal":22,"sortRank":27,"rankEqual":"Y","sortRankTotal":28,"rankTotalEqual":"Y","goldM":0,"silverM":1,"bronzeM":0,"totalM":1,"goldW":0,"silverW":0,"bronzeW":0,"totalW":0,"goldX":0,"silverX":0,"bronzeX":0,"totalX":0,"goldTOT":0,"silverTOT":1,"bronzeTOT":0,"totalTOT":1,"organisationName":"阿塞拜疆","organisationImgUrl":"http://img1.cache.netease.com/pcluster/olympicinfo/post/0d8/415/230/b197b1e5d9ebf5d8cf8d5e8_90x60.jpg","organisationImgUrl19x13":"http://img1.cache.netease.com/pcluster/olympicinfo/post/0d8/415/230/b197b1e5d9ebf5d8cf8d5e8_19x13.jpg"},"organisationName":null,"dateText":null,"organisationImgUrl":null,"organisationImgUrl19x13":null,"disciplineName":null},{"organisation":null,"discipline":null,"province":null,"provinceCode":null,"goldM":0,"silverM":1,"bronzeM":0,"goldW":0,"silverW":0,"bronzeW":0,"goldX":0,"silverX":0,"bronzeX":0,"goldTOT":0,"silverTOT":1,"bronzeTOT":0,"totalTOT":1,"medal":{"organisation":"DEN","rank":27,"rankTotal":22,"sortRank":28,"rankEqual":"Y","sortRankTotal":29,"rankTotalEqual":"Y","goldM":0,"silverM":1,"bronzeM":0,"totalM":1,"goldW":0,"silverW":0,"bronzeW":0,"totalW":0,"goldX":0,"silverX":0,"bronzeX":0,"totalX":0,"goldTOT":0,"silverTOT":1,"bronzeTOT":0,"totalTOT":1,"organisationName":"丹麦","organisationImgUrl":"http://img1.cache.netease.com/pcluster/olympicinfo/post/8df/e24/edd/93b279555d03f146a641928_90x60.jpg","organisationImgUrl19x13":"http://img1.cache.netease.com/pcluster/olympicinfo/post/8df/e24/edd/93b279555d03f146a641928_19x13.jpg"},"organisationName":null,"dateText":null,"organisationImgUrl":null,"organisationImgUrl19x13":null,"disciplineName":null},{"organisation":null,"discipline":null,"province":null,"provinceCode":null,"goldM":0,"silverM":1,"bronzeM":0,"goldW":0,"silverW":0,"bronzeW":0,"goldX":0,"silverX":0,"bronzeX":0,"goldTOT":0,"silverTOT":1,"bronzeTOT":0,"totalTOT":1,"medal":{"organisation":"FRA","rank":27,"rankTotal":22,"sortRank":29,"rankEqual":"Y","sortRankTotal":30,"rankTotalEqual":"Y","goldM":0,"silverM":1,"bronzeM":0,"totalM":1,"goldW":0,"silverW":0,"bronzeW":0,"totalW":0,"goldX":0,"silverX":0,"bronzeX":0,"totalX":0,"goldTOT":0,"silverTOT":1,"bronzeTOT":0,"totalTOT":1,"organisationName":"法国","organisationImgUrl":"http://img1.cache.netease.com/pcluster/olympicinfo/post/9cd/0c5/313/ca7b6966e2d33d1c19e97b9_90x60.jpg","organisationImgUrl19x13":"http://img1.cache.netease.com/pcluster/olympicinfo/post/9cd/0c5/313/ca7b6966e2d33d1c19e97b9_19x13.jpg"},"organisationName":null,"dateText":null,"organisationImgUrl":null,"organisationImgUrl19x13":null,"disciplineName":null},{"organisation":null,"discipline":null,"province":null,"provinceCode":null,"goldM":0,"silverM":0,"bronzeM":0,"goldW":0,"silverW":1,"bronzeW":0,"goldX":0,"silverX":0,"bronzeX":0,"goldTOT":0,"silverTOT":1,"bronzeTOT":0,"totalTOT":1,"medal":{"organisation":"MGL","rank":27,"rankTotal":22,"sortRank":30,"rankEqual":"Y","sortRankTotal":31,"rankTotalEqual":"Y","goldM":0,"silverM":0,"bronzeM":0,"totalM":0,"goldW":0,"silverW":1,"bronzeW":0,"totalW":1,"goldX":0,"silverX":0,"bronzeX":0,"totalX":0,"goldTOT":0,"silverTOT":1,"bronzeTOT":0,"totalTOT":1,"organisationName":"蒙古","organisationImgUrl":"http://img1.cache.netease.com/pcluster/olympicinfo/post/390/8d1/293/7faeda6c8ba1d898605aa9d_90x60.jpg","organisationImgUrl19x13":"http://img1.cache.netease.com/pcluster/olympicinfo/post/390/8d1/293/7faeda6c8ba1d898605aa9d_19x13.jpg"},"organisationName":null,"dateText":null,"organisationImgUrl":null,"organisationImgUrl19x13":null,"disciplineName":null},{"organisation":null,"discipline":null,"province":null,"provinceCode":null,"goldM":0,"silverM":0,"bronzeM":0,"goldW":0,"silverW":1,"bronzeW":0,"goldX":0,"silverX":0,"bronzeX":0,"goldTOT":0,"silverTOT":1,"bronzeTOT":0,"totalTOT":1,"medal":{"organisation":"PHI","rank":27,"rankTotal":22,"sortRank":31,"rankEqual":"Y","sortRankTotal":32,"rankTotalEqual":"Y","goldM":0,"silverM":0,"bronzeM":0,"totalM":0,"goldW":0,"silverW":1,"bronzeW":0,"totalW":1,"goldX":0,"silverX":0,"bronzeX":0,"totalX":0,"goldTOT":0,"silverTOT":1,"bronzeTOT":0,"totalTOT":1,"organisationName":"菲律宾","organisationImgUrl":"http://img1.cache.netease.com/pcluster/olympicinfo/post/d4e/e5e/4cc/640807a1f20b6fc3937614f_90x60.jpg","organisationImgUrl19x13":"http://img1.cache.netease.com/pcluster/olympicinfo/post/d4e/e5e/4cc/640807a1f20b6fc3937614f_19x13.jpg"},"organisationName":null,"dateText":null,"organisationImgUrl":null,"organisationImgUrl19x13":null,"disciplineName":null},{"organisation":null,"discipline":null,"province":null,"provinceCode":null,"goldM":0,"silverM":1,"bronzeM":0,"goldW":0,"silverW":0,"bronzeW":0,"goldX":0,"silverX":0,"bronzeX":0,"goldTOT":0,"silverTOT":1,"bronzeTOT":0,"totalTOT":1,"medal":{"organisation":"PRK","rank":27,"rankTotal":22,"sortRank":32,"rankEqual":"Y","sortRankTotal":33,"rankTotalEqual":"Y","goldM":0,"silverM":1,"bronzeM":0,"totalM":1,"goldW":0,"silverW":0,"bronzeW":0,"totalW":0,"goldX":0,"silverX":0,"bronzeX":0,"totalX":0,"goldTOT":0,"silverTOT":1,"bronzeTOT":0,"totalTOT":1,"organisationName":"朝鲜","organisationImgUrl":"http://img1.cache.netease.com/pcluster/olympicinfo/post/dd2/be1/c68/d8f92ef9ffae8f5b6c2f873_90x60.jpg","organisationImgUrl19x13":"http://img1.cache.netease.com/pcluster/olympicinfo/post/dd2/be1/c68/d8f92ef9ffae8f5b6c2f873_19x13.jpg"},"organisationName":null,"dateText":null,"organisationImgUrl":null,"organisationImgUrl19x13":null,"disciplineName":null},{"organisation":null,"discipline":null,"province":null,"provinceCode":null,"goldM":0,"silverM":0,"bronzeM":2,"goldW":0,"silverW":0,"bronzeW":0,"goldX":0,"silverX":0,"bronzeX":0,"goldTOT":0,"silverTOT":0,"bronzeTOT":2,"totalTOT":2,"medal":{"organisation":"UZB","rank":33,"rankTotal":14,"sortRank":33,"rankEqual":"N","sortRankTotal":21,"rankTotalEqual":"Y","goldM":0,"silverM":0,"bronzeM":2,"totalM":2,"goldW":0,"silverW":0,"bronzeW":0,"totalW":0,"goldX":0,"silverX":0,"bronzeX":0,"totalX":0,"goldTOT":0,"silverTOT":0,"bronzeTOT":2,"totalTOT":2,"organisationName":"乌兹别克斯坦","organisationImgUrl":"http://img1.cache.netease.com/pcluster/olympicinfo/post/bbc/109/361/3b5799e0ff58683db7319ac_90x60.jpg","organisationImgUrl19x13":"http://img1.cache.netease.com/pcluster/olympicinfo/post/bbc/109/361/3b5799e0ff58683db7319ac_19x13.jpg"},"organisationName":null,"dateText":null,"organisationImgUrl":null,"organisationImgUrl19x13":null,"disciplineName":null},{"organisation":null,"discipline":null,"province":null,"provinceCode":null,"goldM":0,"silverM":0,"bronzeM":0,"goldW":0,"silverW":0,"bronzeW":1,"goldX":0,"silverX":0,"bronzeX":0,"goldTOT":0,"silverTOT":0,"bronzeTOT":1,"totalTOT":1,"medal":{"organisation":"ESP","rank":34,"rankTotal":22,"sortRank":34,"rankEqual":"Y","sortRankTotal":34,"rankTotalEqual":"Y","goldM":0,"silverM":0,"bronzeM":0,"totalM":0,"goldW":0,"silverW":0,"bronzeW":1,"totalW":1,"goldX":0,"silverX":0,"bronzeX":0,"totalX":0,"goldTOT":0,"silverTOT":0,"bronzeTOT":1,"totalTOT":1,"organisationName":"西班牙","organisationImgUrl":"http://img1.cache.netease.com/pcluster/olympicinfo/post/61b/2c6/c40/4652521149d7664a49b099a_90x60.jpg","organisationImgUrl19x13":"http://img1.cache.netease.com/pcluster/olympicinfo/post/61b/2c6/c40/4652521149d7664a49b099a_19x13.jpg"},"organisationName":null,"dateText":null,"organisationImgUrl":null,"organisationImgUrl19x13":null,"disciplineName":null},{"organisation":null,"discipline":null,"province":null,"provinceCode":null,"goldM":0,"silverM":0,"bronzeM":1,"goldW":0,"silverW":0,"bronzeW":0,"goldX":0,"silverX":0,"bronzeX":0,"goldTOT":0,"silverTOT":0,"bronzeTOT":1,"totalTOT":1,"medal":{"organisation":"GEO","rank":34,"rankTotal":22,"sortRank":35,"rankEqual":"Y","sortRankTotal":35,"rankTotalEqual":"Y","goldM":0,"silverM":0,"bronzeM":1,"totalM":1,"goldW":0,"silverW":0,"bronzeW":0,"totalW":0,"goldX":0,"silverX":0,"bronzeX":0,"totalX":0,"goldTOT":0,"silverTOT":0,"bronzeTOT":1,"totalTOT":1,"organisationName":"格鲁吉亚","organisationImgUrl":"http://img1.cache.netease.com/pcluster/olympicinfo/post/f22/fe7/d3b/8ae983db2f55cfdc2ff31a7_90x60.jpg","organisationImgUrl19x13":"http://img1.cache.netease.com/pcluster/olympicinfo/post/f22/fe7/d3b/8ae983db2f55cfdc2ff31a7_19x13.jpg"},"organisationName":null,"dateText":null,"organisationImgUrl":null,"organisationImgUrl19x13":null,"disciplineName":null},{"organisation":null,"discipline":null,"province":null,"provinceCode":null,"goldM":0,"silverM":0,"bronzeM":0,"goldW":0,"silverW":0,"bronzeW":1,"goldX":0,"silverX":0,"bronzeX":0,"goldTOT":0,"silverTOT":0,"bronzeTOT":1,"totalTOT":1,"medal":{"organisation":"GRE","rank":34,"rankTotal":22,"sortRank":36,"rankEqual":"Y","sortRankTotal":36,"rankTotalEqual":"Y","goldM":0,"silverM":0,"bronzeM":0,"totalM":0,"goldW":0,"silverW":0,"bronzeW":1,"totalW":1,"goldX":0,"silverX":0,"bronzeX":0,"totalX":0,"goldTOT":0,"silverTOT":0,"bronzeTOT":1,"totalTOT":1,"organisationName":"希腊","organisationImgUrl":"http://img1.cache.netease.com/pcluster/olympicinfo/post/991/def/491/f4dd81bdf5137488af86f41_90x60.jpg","organisationImgUrl19x13":"http://img1.cache.netease.com/pcluster/olympicinfo/post/991/def/491/f4dd81bdf5137488af86f41_19x13.jpg"},"organisationName":null,"dateText":null,"organisationImgUrl":null,"organisationImgUrl19x13":null,"disciplineName":null},{"organisation":null,"discipline":null,"province":null,"provinceCode":null,"goldM":0,"silverM":0,"bronzeM":1,"goldW":0,"silverW":0,"bronzeW":0,"goldX":0,"silverX":0,"bronzeX":0,"goldTOT":0,"silverTOT":0,"bronzeTOT":1,"totalTOT":1,"medal":{"organisation":"POL","rank":34,"rankTotal":22,"sortRank":37,"rankEqual":"Y","sortRankTotal":37,"rankTotalEqual":"Y","goldM":0,"silverM":0,"bronzeM":1,"totalM":1,"goldW":0,"silverW":0,"bronzeW":0,"totalW":0,"goldX":0,"silverX":0,"bronzeX":0,"totalX":0,"goldTOT":0,"silverTOT":0,"bronzeTOT":1,"totalTOT":1,"organisationName":"波兰","organisationImgUrl":"http://img1.cache.netease.com/pcluster/olympicinfo/post/3ef/e0a/a25/0e081be3448f9d70788480b_90x60.jpg","organisationImgUrl19x13":"http://img1.cache.netease.com/pcluster/olympicinfo/post/3ef/e0a/a25/0e081be3448f9d70788480b_19x13.jpg"},"organisationName":null,"dateText":null,"organisationImgUrl":null,"organisationImgUrl19x13":null,"disciplineName":null},{"organisation":null,"discipline":null,"province":null,"provinceCode":null,"goldM":0,"silverM":0,"bronzeM":0,"goldW":0,"silverW":0,"bronzeW":1,"goldX":0,"silverX":0,"bronzeX":0,"goldTOT":0,"silverTOT":0,"bronzeTOT":1,"totalTOT":1,"medal":{"organisation":"POR","rank":34,"rankTotal":22,"sortRank":38,"rankEqual":"Y","sortRankTotal":38,"rankTotalEqual":"Y","goldM":0,"silverM":0,"bronzeM":0,"totalM":0,"goldW":0,"silverW":0,"bronzeW":1,"totalW":1,"goldX":0,"silverX":0,"bronzeX":0,"totalX":0,"goldTOT":0,"silverTOT":0,"bronzeTOT":1,"totalTOT":1,"organisationName":"葡萄牙","organisationImgUrl":"http://img1.cache.netease.com/pcluster/olympicinfo/post/e92/e73/7a1/3975fc2b8a77d517e69bd48_90x60.jpg","organisationImgUrl19x13":"http://img1.cache.netease.com/pcluster/olympicinfo/post/e92/e73/7a1/3975fc2b8a77d517e69bd48_19x13.jpg"},"organisationName":null,"dateText":null,"organisationImgUrl":null,"organisationImgUrl19x13":null,"disciplineName":null}],"goldM":19,"silverM":19,"bronzeM":22,"goldW":21,"silverW":21,"bronzeW":25,"goldX":0,"silverX":0,"bronzeX":0,"goldTOT":40,"silverTOT":40,"bronzeTOT":47,"totalTOT":127}